LICENSE
MANIFEST.in
README.md
setup.py
mkdocs_link_preview_plugin/__init__.py
mkdocs_link_preview_plugin/opengraph.py
mkdocs_link_preview_plugin/plugin.py
mkdocs_link_preview_plugin.egg-info/PKG-INFO
mkdocs_link_preview_plugin.egg-info/SOURCES.txt
mkdocs_link_preview_plugin.egg-info/dependency_links.txt
mkdocs_link_preview_plugin.egg-info/entry_points.txt
mkdocs_link_preview_plugin.egg-info/requires.txt
mkdocs_link_preview_plugin.egg-info/top_level.txt
mkdocs_link_preview_plugin/resources/fallback.html
mkdocs_link_preview_plugin/resources/link-preview.css
mkdocs_link_preview_plugin/resources/preview.html