Metadata-Version: 2.1
Name: mkdocs-link-preview-plugin
Version: 0.3.1
Summary: A MkDocs plugin that supports external link preview
Home-page: https://github.com/ndy2/mkdocs-link-preview-plugin
Author: ndy2
Author-email: emrdbs12@gmail.com
License: MIT
Keywords: mkdocs
Classifier: Development Status :: 4 - Beta
Classifier: Intended Audience :: Developers
Classifier: Intended Audience :: Information Technology
Classifier: License :: OSI Approved :: MIT License
Classifier: Programming Language :: Python
Classifier: Programming Language :: Python :: 3 :: Only
Classifier: Programming Language :: Python :: 3.4
Classifier: Programming Language :: Python :: 3.5
Classifier: Programming Language :: Python :: 3.6
Classifier: Programming Language :: Python :: 3.7
Requires-Python: >=2.7
License-File: LICENSE
